initor_bot_inference/__init__.py
initor_bot_inference/fast_reid/.github/FastReID-Logo.png
initor_bot_inference/fast_reid/.github/ISSUE_TEMPLATE/bugs.md
initor_bot_inference/fast_reid/.github/ISSUE_TEMPLATE/config.yml
initor_bot_inference/fast_reid/.github/ISSUE_TEMPLATE/questions-help-support.md
initor_bot_inference/fast_reid/.github/ISSUE_TEMPLATE/unexpected-problems-bugs.md
initor_bot_inference/fast_reid/.github/wechat_group.png
initor_bot_inference/fast_reid/.github/workflows/issue_auto_close.yml
initor_bot_inference/fast_reid/.github/workflows/lint_python.yml
initor_bot_inference/fast_reid/.gitignore
initor_bot_inference/fast_reid/CHANGELOG.md
initor_bot_inference/fast_reid/GETTING_STARTED.md
initor_bot_inference/fast_reid/INSTALL.md
initor_bot_inference/fast_reid/LICENSE
initor_bot_inference/fast_reid/MODEL_ZOO.md
initor_bot_inference/fast_reid/README.md
initor_bot_inference/fast_reid/configs/Base-AGW.yml
initor_bot_inference/fast_reid/configs/Base-MGN.yml
initor_bot_inference/fast_reid/configs/Base-SBS.yml
initor_bot_inference/fast_reid/configs/Base-bagtricks.yml
initor_bot_inference/fast_reid/configs/DukeMTMC/AGW_R101-ibn.yml
initor_bot_inference/fast_reid/configs/DukeMTMC/AGW_R50-ibn.yml
initor_bot_inference/fast_reid/configs/DukeMTMC/AGW_R50.yml
initor_bot_inference/fast_reid/configs/DukeMTMC/AGW_S50.yml
initor_bot_inference/fast_reid/configs/DukeMTMC/bagtricks_R101-ibn.yml
initor_bot_inference/fast_reid/configs/DukeMTMC/bagtricks_R50-ibn.yml
initor_bot_inference/fast_reid/configs/DukeMTMC/bagtricks_R50.yml
initor_bot_inference/fast_reid/configs/DukeMTMC/bagtricks_S50.yml
initor_bot_inference/fast_reid/configs/DukeMTMC/mgn_R50-ibn.yml
initor_bot_inference/fast_reid/configs/DukeMTMC/sbs_R101-ibn.yml
initor_bot_inference/fast_reid/configs/DukeMTMC/sbs_R50-ibn.yml
initor_bot_inference/fast_reid/configs/DukeMTMC/sbs_R50.yml
initor_bot_inference/fast_reid/configs/DukeMTMC/sbs_S50.yml
initor_bot_inference/fast_reid/configs/MOT17/AGW_R101-ibn.yml
initor_bot_inference-2.0.5.dist-info/WHEEL
initor_bot_inference-2.0.5.dist-info/METADATA
initor_bot_inference-2.0.5.dist-info/RECORD
