Metadata-Version: 2.1
Name: initor-bot-inference
Version: 2.0.5
Summary: 
Author: s
Requires-Python: >=3.8,<4.0
Classifier: Programming Language :: Python :: 3
Classifier: Programming Language :: Python :: 3.10
Classifier: Programming Language :: Python :: 3.8
Classifier: Programming Language :: Python :: 3.9
Requires-Dist: Pillow (>=10.0.0,<11.0.0)
Requires-Dist: PyYAML (>=6.0,<7.0)
Requires-Dist: easydict (>=1.10,<2.0)
Requires-Dist: filterpy (>=1.4.5,<2.0.0)
Requires-Dist: gdown (>=4.7.1,<5.0.0)
Requires-Dist: h5py (>=3.9.0,<4.0.0)
Requires-Dist: lap (>=0.4.0,<0.5.0)
Requires-Dist: loguru (>=0.7.0,<0.8.0)
Requires-Dist: matplotlib (>=3.7.2,<4.0.0)
Requires-Dist: motmetrics (>=1.4.0,<2.0.0)
Requires-Dist: ninja (>=1.11.1,<2.0.0)
Requires-Dist: numpy (==1.23.5)
Requires-Dist: onnx (==1.8.1)
Requires-Dist: onnx-simplifier (==0.3.5)
Requires-Dist: onnxruntime (==1.8.0)
Requires-Dist: opencv-python (>=4.8.0,<5.0.0)
Requires-Dist: prettytable (>=3.8.0,<4.0.0)
Requires-Dist: scikit-image (>=0.21.0,<0.22.0)
Requires-Dist: scikit-learn (>=1.3.0,<2.0.0)
Requires-Dist: scipy (<1.11.1)
Requires-Dist: tabulate (>=0.9.0,<0.10.0)
Requires-Dist: tensorboard (>=2.13.0,<3.0.0)
Requires-Dist: termcolor (>=2.3.0,<3.0.0)
Requires-Dist: thop (>=0.1.1,<0.2.0)
Requires-Dist: torchvision (==0.12.0)
Requires-Dist: tqdm (>=4.65.0,<5.0.0)
Requires-Dist: yacs (>=0.1.8,<0.2.0)
